styletx/StyleTransfer.py
styletx/__init__.py
styletx/process.py
styletx-1.0.5.dist-info/METADATA
styletx-1.0.5.dist-info/WHEEL
styletx-1.0.5.dist-info/top_level.txt
styletx-1.0.5.dist-info/RECORD
