Metadata-Version: 2.1
Name: styletx
Version: 1.0.5
Summary: Initial release with StyleTransfer
Home-page: https://github.com/dinesh-GDK/StyleTx
Author: Dinesh Kumar Gnanasekaran
Author-email: dinesh.gna111@gmail.com
License: MIT
Platform: UNKNOWN
Requires-Python: >3.8
